{
  "last_conjunto": "12-03-2026 10:21:02 UTC",
  "last_run": "2026-03-12T10:21:55.076157+00:00",
  "alerts_history": {
    "1487": {
      "cod_alerta": "1487",
      "datahoracriacao": "2026-03-10 13:45:12.115",
      "ult_atualizacao": "2026-03-10 13:45:12.115",
      "codibge": "3131703",
      "evento": "Movimentos de Massa - Moderado",
      "nivel": "Moderado",
      "status": 1,
      "uf": "MG",
      "municipio": "ITABIRA",
      "latitude": -19.600608398588,
      "longitude": -43.29991272009,
      "created_at_iso": "2026-03-10T13:45:12.115000+00:00",
      "updated_at_iso": "2026-03-10T13:45:12.115000+00:00",
      "first_seen_at": "2026-03-12T10:21:55.076157+00:00",
      "last_seen_at": "2026-03-12T10:21:55.076157+00:00"
    },
    "1488": {
      "cod_alerta": "1488",
      "datahoracriacao": "2026-03-10 13:47:11.245",
      "ult_atualizacao": "2026-03-10 13:47:11.245",
      "codibge": "3118601",
      "evento": "Movimentos de Massa - Moderado",
      "nivel": "Moderado",
      "status": 1,
      "uf": "MG",
      "municipio": "CONTAGEM",
      "latitude": -19.887353851292,
      "longitude": -44.083929048253,
      "created_at_iso": "2026-03-10T13:47:11.245000+00:00",
      "updated_at_iso": "2026-03-10T13:47:11.245000+00:00",
      "first_seen_at": "2026-03-12T10:21:55.076157+00:00",
      "last_seen_at": "2026-03-12T10:21:55.076157+00:00"
    },
    "1489": {
      "cod_alerta": "1489",
      "datahoracriacao": "2026-03-10 15:06:59.393",
      "ult_atualizacao": "2026-03-10 15:06:59.393",
      "codibge": "3129301",
      "evento": "Movimentos de Massa - Moderado",
      "nivel": "Moderado",
      "status": 1,
      "uf": "MG",
      "municipio": "IAPU",
      "latitude": -19.347115188889,
      "longitude": -42.242751178561,
      "created_at_iso": "2026-03-10T15:06:59.393000+00:00",
      "updated_at_iso": "2026-03-10T15:06:59.393000+00:00",
      "first_seen_at": "2026-03-12T10:21:55.076157+00:00",
      "last_seen_at": "2026-03-12T10:21:55.076157+00:00"
    },
    "1490": {
      "cod_alerta": "1490",
      "datahoracriacao": "2026-03-10 15:33:10.422",
      "ult_atualizacao": "2026-03-10 15:33:10.422",
      "codibge": "3136207",
      "evento": "Movimentos de Massa - Moderado",
      "nivel": "Moderado",
      "status": 1,
      "uf": "MG",
      "municipio": "JOÃO MONLEVADE",
      "latitude": -19.837941198792,
      "longitude": -43.161486132665,
      "created_at_iso": "2026-03-10T15:33:10.422000+00:00",
      "updated_at_iso": "2026-03-10T15:33:10.422000+00:00",
      "first_seen_at": "2026-03-12T10:21:55.076157+00:00",
      "last_seen_at": "2026-03-12T10:21:55.076157+00:00"
    },
    "1491": {
      "cod_alerta": "1491",
      "datahoracriacao": "2026-03-10 16:35:31.574",
      "ult_atualizacao": "2026-03-10 16:35:31.574",
      "codibge": "3116001",
      "evento": "Movimentos de Massa - Moderado",
      "nivel": "Moderado",
      "status": 1,
      "uf": "MG",
      "municipio": "CHALÉ",
      "latitude": -20.030977814818,
      "longitude": -41.659783517698,
      "created_at_iso": "2026-03-10T16:35:31.574000+00:00",
      "updated_at_iso": "2026-03-10T16:35:31.574000+00:00",
      "first_seen_at": "2026-03-12T10:21:55.076157+00:00",
      "last_seen_at": "2026-03-12T10:21:55.076157+00:00"
    },
    "1493": {
      "cod_alerta": "1493",
      "datahoracriacao": "2026-03-10 19:33:15.611",
      "ult_atualizacao": "2026-03-10 19:33:15.611",
      "codibge": "3200169",
      "evento": "Movimentos de Massa - Moderado",
      "nivel": "Moderado",
      "status": 1,
      "uf": "ES",
      "municipio": "ÁGUA DOCE DO NORTE",
      "latitude": -18.516648875905,
      "longitude": -40.996758627489,
      "created_at_iso": "2026-03-10T19:33:15.611000+00:00",
      "updated_at_iso": "2026-03-10T19:33:15.611000+00:00",
      "first_seen_at": "2026-03-12T10:21:55.076157+00:00",
      "last_seen_at": "2026-03-12T10:21:55.076157+00:00"
    },
    "1496": {
      "cod_alerta": "1496",
      "datahoracriacao": "2026-03-11 03:35:09.758",
      "ult_atualizacao": "2026-03-11 03:35:09.758",
      "codibge": "2902708",
      "evento": "Risco Hidrológico - Alto",
      "nivel": "Alto",
      "status": 1,
      "uf": "BA",
      "municipio": "BARRA",
      "latitude": -11.031844588599,
      "longitude": -43.366821769166,
      "created_at_iso": "2026-03-11T03:35:09.758000+00:00",
      "updated_at_iso": "2026-03-11T03:35:09.758000+00:00",
      "first_seen_at": "2026-03-12T10:21:55.076157+00:00",
      "last_seen_at": "2026-03-12T10:21:55.076157+00:00"
    },
    "1502": {
      "cod_alerta": "1502",
      "datahoracriacao": "2026-03-11 16:17:22.135",
      "ult_atualizacao": "2026-03-11 16:17:22.135",
      "codibge": "3140001",
      "evento": "Movimentos de Massa - Moderado",
      "nivel": "Moderado",
      "status": 1,
      "uf": "MG",
      "municipio": "MARIANA",
      "latitude": -20.32910250416,
      "longitude": -43.331334041862,
      "created_at_iso": "2026-03-11T16:17:22.135000+00:00",
      "updated_at_iso": "2026-03-11T16:17:22.135000+00:00",
      "first_seen_at": "2026-03-12T10:21:55.076157+00:00",
      "last_seen_at": "2026-03-12T10:21:55.076157+00:00"
    },
    "1503": {
      "cod_alerta": "1503",
      "datahoracriacao": "2026-03-11 16:36:08.522",
      "ult_atualizacao": "2026-03-11 16:36:08.522",
      "codibge": "3118304",
      "evento": "Risco Hidrológico - Moderado",
      "nivel": "Moderado",
      "status": 1,
      "uf": "MG",
      "municipio": "CONSELHEIRO LAFAIETE",
      "latitude": -20.666008441146,
      "longitude": -43.788656797159,
      "created_at_iso": "2026-03-11T16:36:08.522000+00:00",
      "updated_at_iso": "2026-03-11T16:36:08.522000+00:00",
      "first_seen_at": "2026-03-12T10:21:55.076157+00:00",
      "last_seen_at": "2026-03-12T10:21:55.076157+00:00"
    },
    "1504": {
      "cod_alerta": "1504",
      "datahoracriacao": "2026-03-11 16:40:22.876",
      "ult_atualizacao": "2026-03-11 16:40:22.876",
      "codibge": "3140001",
      "evento": "Risco Hidrológico - Moderado",
      "nivel": "Moderado",
      "status": 1,
      "uf": "MG",
      "municipio": "MARIANA",
      "latitude": -20.32910250416,
      "longitude": -43.331334041862,
      "created_at_iso": "2026-03-11T16:40:22.876000+00:00",
      "updated_at_iso": "2026-03-11T16:40:22.876000+00:00",
      "first_seen_at": "2026-03-12T10:21:55.076157+00:00",
      "last_seen_at": "2026-03-12T10:21:55.076157+00:00"
    },
    "1505": {
      "cod_alerta": "1505",
      "datahoracriacao": "2026-03-11 16:41:23.555",
      "ult_atualizacao": "2026-03-11 16:41:23.555",
      "codibge": "3118304",
      "evento": "Movimentos de Massa - Moderado",
      "nivel": "Moderado",
      "status": 1,
      "uf": "MG",
      "municipio": "CONSELHEIRO LAFAIETE",
      "latitude": -20.666008441146,
      "longitude": -43.788656797159,
      "created_at_iso": "2026-03-11T16:41:23.555000+00:00",
      "updated_at_iso": "2026-03-11T16:41:23.555000+00:00",
      "first_seen_at": "2026-03-12T10:21:55.076157+00:00",
      "last_seen_at": "2026-03-12T10:21:55.076157+00:00"
    },
    "1506": {
      "cod_alerta": "1506",
      "datahoracriacao": "2026-03-11 16:43:00.81",
      "ult_atualizacao": "2026-03-11 16:43:00.81",
      "codibge": "5300108",
      "evento": "Risco Hidrológico - Moderado",
      "nivel": "Moderado",
      "status": 1,
      "uf": "DF",
      "municipio": "BRASÍLIA",
      "latitude": -15.780692384702,
      "longitude": -47.797360713196,
      "created_at_iso": "2026-03-11T16:43:00.810000+00:00",
      "updated_at_iso": "2026-03-11T16:43:00.810000+00:00",
      "first_seen_at": "2026-03-12T10:21:55.076157+00:00",
      "last_seen_at": "2026-03-12T10:21:55.076157+00:00"
    },
    "1501": {
      "cod_alerta": "1501",
      "datahoracriacao": "2026-03-11 15:56:40.887",
      "ult_atualizacao": "2026-03-11 17:17:10.584",
      "codibge": "3106200",
      "evento": "Risco Hidrológico - Alto",
      "nivel": "Alto",
      "status": 1,
      "uf": "MG",
      "municipio": "BELO HORIZONTE",
      "latitude": -19.902739296534,
      "longitude": -43.959883509799,
      "created_at_iso": "2026-03-11T15:56:40.887000+00:00",
      "updated_at_iso": "2026-03-11T17:17:10.584000+00:00",
      "first_seen_at": "2026-03-12T10:21:55.076157+00:00",
      "last_seen_at": "2026-03-12T10:21:55.076157+00:00"
    },
    "1507": {
      "cod_alerta": "1507",
      "datahoracriacao": "2026-03-11 17:31:53.085",
      "ult_atualizacao": "2026-03-11 17:31:53.085",
      "codibge": "3139508",
      "evento": "Movimentos de Massa - Moderado",
      "nivel": "Moderado",
      "status": 1,
      "uf": "MG",
      "municipio": "MANHUMIRIM",
      "latitude": -20.347320794114,
      "longitude": -41.939402204186,
      "created_at_iso": "2026-03-11T17:31:53.085000+00:00",
      "updated_at_iso": "2026-03-11T17:31:53.085000+00:00",
      "first_seen_at": "2026-03-12T10:21:55.076157+00:00",
      "last_seen_at": "2026-03-12T10:21:55.076157+00:00"
    },
    "1508": {
      "cod_alerta": "1508",
      "datahoracriacao": "2026-03-11 19:24:38.296",
      "ult_atualizacao": "2026-03-11 19:24:38.296",
      "codibge": "3203700",
      "evento": "Risco Hidrológico - Moderado",
      "nivel": "Moderado",
      "status": 1,
      "uf": "ES",
      "municipio": "MUNIZ FREIRE",
      "latitude": -20.426772479082,
      "longitude": -41.43502364366,
      "created_at_iso": "2026-03-11T19:24:38.296000+00:00",
      "updated_at_iso": "2026-03-11T19:24:38.296000+00:00",
      "first_seen_at": "2026-03-12T10:21:55.076157+00:00",
      "last_seen_at": "2026-03-12T10:21:55.076157+00:00"
    },
    "1510": {
      "cod_alerta": "1510",
      "datahoracriacao": "2026-03-11 22:02:04.183",
      "ult_atualizacao": "2026-03-11 22:02:04.183",
      "codibge": "3508801",
      "evento": "Risco Hidrológico - Moderado",
      "nivel": "Moderado",
      "status": 1,
      "uf": "SP",
      "municipio": "CAFELÂNDIA",
      "latitude": -21.731130617942,
      "longitude": -49.54863038916,
      "created_at_iso": "2026-03-11T22:02:04.183000+00:00",
      "updated_at_iso": "2026-03-11T22:02:04.183000+00:00",
      "first_seen_at": "2026-03-12T10:21:55.076157+00:00",
      "last_seen_at": "2026-03-12T10:21:55.076157+00:00"
    },
    "1511": {
      "cod_alerta": "1511",
      "datahoracriacao": "2026-03-11 23:04:49.79",
      "ult_atualizacao": "2026-03-11 23:04:49.79",
      "codibge": "3158953",
      "evento": "Risco Hidrológico - Moderado",
      "nivel": "Moderado",
      "status": 1,
      "uf": "MG",
      "municipio": "SANTANA DO PARAÍSO",
      "latitude": -19.385069660852,
      "longitude": -42.52047448932,
      "created_at_iso": "2026-03-11T23:04:49.790000+00:00",
      "updated_at_iso": "2026-03-11T23:04:49.790000+00:00",
      "first_seen_at": "2026-03-12T10:21:55.076157+00:00",
      "last_seen_at": "2026-03-12T10:21:55.076157+00:00"
    },
    "1512": {
      "cod_alerta": "1512",
      "datahoracriacao": "2026-03-11 23:15:07.088",
      "ult_atualizacao": "2026-03-11 23:15:07.088",
      "codibge": "3131307",
      "evento": "Risco Hidrológico - Moderado",
      "nivel": "Moderado",
      "status": 1,
      "uf": "MG",
      "municipio": "IPATINGA",
      "latitude": -19.438972749232,
      "longitude": -42.600921984069,
      "created_at_iso": "2026-03-11T23:15:07.088000+00:00",
      "updated_at_iso": "2026-03-11T23:15:07.088000+00:00",
      "first_seen_at": "2026-03-12T10:21:55.076157+00:00",
      "last_seen_at": "2026-03-12T10:21:55.076157+00:00"
    },
    "1513": {
      "cod_alerta": "1513",
      "datahoracriacao": "2026-03-12 00:44:28.432",
      "ult_atualizacao": "2026-03-12 00:44:28.432",
      "codibge": "3119401",
      "evento": "Risco Hidrológico - Moderado",
      "nivel": "Moderado",
      "status": 1,
      "uf": "MG",
      "municipio": "CORONEL FABRICIANO",
      "latitude": -19.458587479076,
      "longitude": -42.689925045198,
      "created_at_iso": "2026-03-12T00:44:28.432000+00:00",
      "updated_at_iso": "2026-03-12T00:44:28.432000+00:00",
      "first_seen_at": "2026-03-12T10:21:55.076157+00:00",
      "last_seen_at": "2026-03-12T10:21:55.076157+00:00"
    },
    "1514": {
      "cod_alerta": "1514",
      "datahoracriacao": "2026-03-12 00:47:35.605",
      "ult_atualizacao": "2026-03-12 00:47:35.605",
      "codibge": "3131307",
      "evento": "Movimentos de Massa - Moderado",
      "nivel": "Moderado",
      "status": 1,
      "uf": "MG",
      "municipio": "IPATINGA",
      "latitude": -19.438972749232,
      "longitude": -42.600921984069,
      "created_at_iso": "2026-03-12T00:47:35.605000+00:00",
      "updated_at_iso": "2026-03-12T00:47:35.605000+00:00",
      "first_seen_at": "2026-03-12T10:21:55.076157+00:00",
      "last_seen_at": "2026-03-12T10:21:55.076157+00:00"
    },
    "1515": {
      "cod_alerta": "1515",
      "datahoracriacao": "2026-03-12 01:36:17.974",
      "ult_atualizacao": "2026-03-12 01:36:17.974",
      "codibge": "3158953",
      "evento": "Movimentos de Massa - Moderado",
      "nivel": "Moderado",
      "status": 1,
      "uf": "MG",
      "municipio": "SANTANA DO PARAÍSO",
      "latitude": -19.385069660852,
      "longitude": -42.52047448932,
      "created_at_iso": "2026-03-12T01:36:17.974000+00:00",
      "updated_at_iso": "2026-03-12T01:36:17.974000+00:00",
      "first_seen_at": "2026-03-12T10:21:55.076157+00:00",
      "last_seen_at": "2026-03-12T10:21:55.076157+00:00"
    },
    "1516": {
      "cod_alerta": "1516",
      "datahoracriacao": "2026-03-12 03:27:33.024",
      "ult_atualizacao": "2026-03-12 03:27:33.024",
      "codibge": "3529005",
      "evento": "Movimentos de Massa - Moderado",
      "nivel": "Moderado",
      "status": 1,
      "uf": "SP",
      "municipio": "MARÍLIA",
      "latitude": -22.178295267989,
      "longitude": -49.983025395743,
      "created_at_iso": "2026-03-12T03:27:33.024000+00:00",
      "updated_at_iso": "2026-03-12T03:27:33.024000+00:00",
      "first_seen_at": "2026-03-12T10:21:55.076157+00:00",
      "last_seen_at": "2026-03-12T10:21:55.076157+00:00"
    },
    "1517": {
      "cod_alerta": "1517",
      "datahoracriacao": "2026-03-12 03:45:50.763",
      "ult_atualizacao": "2026-03-12 03:45:50.763",
      "codibge": "3529005",
      "evento": "Risco Hidrológico - Moderado",
      "nivel": "Moderado",
      "status": 1,
      "uf": "SP",
      "municipio": "MARÍLIA",
      "latitude": -22.178295267989,
      "longitude": -49.983025395743,
      "created_at_iso": "2026-03-12T03:45:50.763000+00:00",
      "updated_at_iso": "2026-03-12T03:45:50.763000+00:00",
      "first_seen_at": "2026-03-12T10:21:55.076157+00:00",
      "last_seen_at": "2026-03-12T10:21:55.076157+00:00"
    },
    "1518": {
      "cod_alerta": "1518",
      "datahoracriacao": "2026-03-12 03:56:30.635",
      "ult_atualizacao": "2026-03-12 03:56:30.635",
      "codibge": "3543907",
      "evento": "Risco Hidrológico - Moderado",
      "nivel": "Moderado",
      "status": 1,
      "uf": "SP",
      "municipio": "RIO CLARO",
      "latitude": -22.373917585514,
      "longitude": -47.579894394705,
      "created_at_iso": "2026-03-12T03:56:30.635000+00:00",
      "updated_at_iso": "2026-03-12T03:56:30.635000+00:00",
      "first_seen_at": "2026-03-12T10:21:55.076157+00:00",
      "last_seen_at": "2026-03-12T10:21:55.076157+00:00"
    },
    "1519": {
      "cod_alerta": "1519",
      "datahoracriacao": "2026-03-12 03:59:04.225",
      "ult_atualizacao": "2026-03-12 03:59:04.225",
      "codibge": "3523404",
      "evento": "Risco Hidrológico - Moderado",
      "nivel": "Moderado",
      "status": 1,
      "uf": "SP",
      "municipio": "ITATIBA",
      "latitude": -23.006717264789,
      "longitude": -46.814296833428,
      "created_at_iso": "2026-03-12T03:59:04.225000+00:00",
      "updated_at_iso": "2026-03-12T03:59:04.225000+00:00",
      "first_seen_at": "2026-03-12T10:21:55.076157+00:00",
      "last_seen_at": "2026-03-12T10:21:55.076157+00:00"
    },
    "1521": {
      "cod_alerta": "1521",
      "datahoracriacao": "2026-03-12 05:45:25.684",
      "ult_atualizacao": "2026-03-12 05:45:25.684",
      "codibge": "3524006",
      "evento": "Movimentos de Massa - Moderado",
      "nivel": "Moderado",
      "status": 1,
      "uf": "SP",
      "municipio": "ITUPEVA",
      "latitude": -23.146514144169,
      "longitude": -47.068403089877,
      "created_at_iso": "2026-03-12T05:45:25.684000+00:00",
      "updated_at_iso": "2026-03-12T05:45:25.684000+00:00",
      "first_seen_at": "2026-03-12T10:21:55.076157+00:00",
      "last_seen_at": "2026-03-12T10:21:55.076157+00:00"
    },
    "1520": {
      "cod_alerta": "1520",
      "datahoracriacao": "2026-03-12 04:57:52.781",
      "ult_atualizacao": "2026-03-12 05:53:53.072",
      "codibge": "1503705",
      "evento": "Risco Hidrológico - Alto",
      "nivel": "Alto",
      "status": 1,
      "uf": "PA",
      "municipio": "ITUPIRANGA",
      "latitude": -5.1148242573386,
      "longitude": -49.869706058481,
      "created_at_iso": "2026-03-12T04:57:52.781000+00:00",
      "updated_at_iso": "2026-03-12T05:53:53.072000+00:00",
      "first_seen_at": "2026-03-12T10:21:55.076157+00:00",
      "last_seen_at": "2026-03-12T10:21:55.076157+00:00"
    }
  },
  "last_24h_signature": "1501|2026-03-11T15:56:40.887000+00:00|Alto|Risco Hidrológico - Alto||1502|2026-03-11T16:17:22.135000+00:00|Moderado|Movimentos de Massa - Moderado||1503|2026-03-11T16:36:08.522000+00:00|Moderado|Risco Hidrológico - Moderado||1504|2026-03-11T16:40:22.876000+00:00|Moderado|Risco Hidrológico - Moderado||1505|2026-03-11T16:41:23.555000+00:00|Moderado|Movimentos de Massa - Moderado||1506|2026-03-11T16:43:00.810000+00:00|Moderado|Risco Hidrológico - Moderado||1507|2026-03-11T17:31:53.085000+00:00|Moderado|Movimentos de Massa - Moderado||1508|2026-03-11T19:24:38.296000+00:00|Moderado|Risco Hidrológico - Moderado||1510|2026-03-11T22:02:04.183000+00:00|Moderado|Risco Hidrológico - Moderado||1511|2026-03-11T23:04:49.790000+00:00|Moderado|Risco Hidrológico - Moderado||1512|2026-03-11T23:15:07.088000+00:00|Moderado|Risco Hidrológico - Moderado||1513|2026-03-12T00:44:28.432000+00:00|Moderado|Risco Hidrológico - Moderado||1514|2026-03-12T00:47:35.605000+00:00|Moderado|Movimentos de Massa - Moderado||1515|2026-03-12T01:36:17.974000+00:00|Moderado|Movimentos de Massa - Moderado||1516|2026-03-12T03:27:33.024000+00:00|Moderado|Movimentos de Massa - Moderado||1517|2026-03-12T03:45:50.763000+00:00|Moderado|Risco Hidrológico - Moderado||1518|2026-03-12T03:56:30.635000+00:00|Moderado|Risco Hidrológico - Moderado||1519|2026-03-12T03:59:04.225000+00:00|Moderado|Risco Hidrológico - Moderado||1520|2026-03-12T04:57:52.781000+00:00|Alto|Risco Hidrológico - Alto||1521|2026-03-12T05:45:25.684000+00:00|Moderado|Movimentos de Massa - Moderado"
}